{
  "account_id": "6d65226e-669f-5537-84ef-1d0e937076f3",
  "account_name": "Quarrymill Fleet Ops",
  "account_slug": "quarrymill-fleet-ops",
  "app_events": [
    {
      "account_id": "6d65226e-669f-5537-84ef-1d0e937076f3",
      "confidence": "synthetic_truth",
      "day_offset": 140,
      "event_id": "1160784a-5185-5698-bfbd-d43ecac32697",
      "event_type": "account_viewed",
      "feature": "account_workspace",
      "object_id": "ae78456e-e951-54d5-9307-91c068b74e08",
      "object_type": "account",
      "observed_at": "2026-11-08T01:00:00Z",
      "properties": {
        "archetype": "risk_watch",
        "health_band": "yellow",
        "lifecycle_stage": "steady_state",
        "perturbation_bucket": 2
      },
      "route": "/account/6d65226e-669f-5537-84ef-1d0e937076f3",
      "source_ref": "centralize_app:mcp_api_simulated",
      "user_id": "csm-101"
    },
    {
      "account_id": "6d65226e-669f-5537-84ef-1d0e937076f3",
      "confidence": "synthetic_truth",
      "day_offset": 140,
      "event_id": "e534dd9e-6ba0-5a58-8f42-2fbf4982a97f",
      "event_type": "health_record_viewed",
      "feature": "health",
      "object_id": "ad4bf88e-cab9-554b-bb02-a3985705ab61",
      "object_type": "health_score",
      "observed_at": "2026-11-08T01:00:00Z",
      "properties": {
        "acted": false,
        "archetype": "risk_watch",
        "current_band": "yellow",
        "health_band": "yellow",
        "lifecycle_stage": "steady_state",
        "perturbation_bucket": 2
      },
      "route": "/account/6d65226e-669f-5537-84ef-1d0e937076f3/reporting",
      "source_ref": "centralize_app:mcp_api_simulated",
      "user_id": "csm-101"
    },
    {
      "account_id": "6d65226e-669f-5537-84ef-1d0e937076f3",
      "confidence": "synthetic_truth",
      "day_offset": 140,
      "event_id": "4a16d195-1af3-5696-84c9-054a1a643df9",
      "event_type": "contact_profile_opened",
      "feature": "contacts",
      "object_id": "6f8a3947-f2ed-540d-99ab-3ee540a3ea24",
      "object_type": "contact",
      "observed_at": "2026-11-08T02:00:00Z",
      "properties": {
        "archetype": "risk_watch",
        "contact_role": "champion",
        "engagement_state": "quiet",
        "health_band": "yellow",
        "lifecycle_stage": "steady_state",
        "perturbation_bucket": 2
      },
      "route": "/account/6d65226e-669f-5537-84ef-1d0e937076f3/contacts",
      "source_ref": "centralize_app:mcp_api_simulated",
      "user_id": "csm-101"
    },
    {
      "account_id": "6d65226e-669f-5537-84ef-1d0e937076f3",
      "confidence": "inferred_route",
      "day_offset": 140,
      "event_id": "c9595e78-4127-5b6d-b348-1fe3ee6e3e76",
      "event_type": "saved_view_opened",
      "feature": "accounts",
      "object_id": "adb1db6e-d057-5ffa-a653-080f76cdca75",
      "object_type": "saved_view",
      "observed_at": "2026-11-08T04:00:00Z",
      "properties": {
        "active_users": 12,
        "archetype": "risk_watch",
        "health_band": "yellow",
        "lifecycle_stage": "steady_state",
        "noise_class": "perturbed_app_exhaust",
        "perturbation_bucket": 2
      },
      "route": "/accounts",
      "source_ref": "centralize_app:mcp_api_simulated",
      "user_id": "csm-101"
    },
    {
      "account_id": "6d65226e-669f-5537-84ef-1d0e937076f3",
      "confidence": "inferred_route",
      "day_offset": 140,
      "event_id": "490e4c99-25cb-5b44-91ec-a618ab7fa84e",
      "event_type": "contact_search_performed",
      "feature": "contacts",
      "object_id": "f4a14a61-8c18-57a6-85be-0cb7aeba1208",
      "object_type": "search",
      "observed_at": "2026-11-08T05:00:00Z",
      "properties": {
        "active_users": 12,
        "archetype": "risk_watch",
        "health_band": "yellow",
        "lifecycle_stage": "steady_state",
        "noise_class": "perturbed_app_exhaust",
        "perturbation_bucket": 2
      },
      "route": "/contacts",
      "source_ref": "centralize_app:mcp_api_simulated",
      "user_id": "csm-101"
    },
    {
      "account_id": "6d65226e-669f-5537-84ef-1d0e937076f3",
      "confidence": "inferred_route",
      "day_offset": 140,
      "event_id": "06c18e7d-7019-5667-aed9-b1d683d11cb5",
      "event_type": "note_viewed",
      "feature": "notes",
      "object_id": "198d91d2-b1d7-5849-9048-15db4f93d8f3",
      "object_type": "note",
      "observed_at": "2026-11-08T06:00:00Z",
      "properties": {
        "active_users": 12,
        "archetype": "risk_watch",
        "health_band": "yellow",
        "lifecycle_stage": "steady_state",
        "noise_class": "perturbed_app_exhaust",
        "perturbation_bucket": 2
      },
      "route": "/account/6d65226e-669f-5537-84ef-1d0e937076f3/notes",
      "source_ref": "centralize_app:mcp_api_simulated",
      "user_id": "csm-101"
    }
  ],
  "as_of": "2026-11-08",
  "day_offset": 140,
  "derived_usage_signals": [
    {
      "account_id": "6d65226e-669f-5537-84ef-1d0e937076f3",
      "grain": "company",
      "metric_name": "centralize_account_views",
      "observed_at": "2026-11-08T14:00:00Z",
      "signal_id": "3668844f-be0d-5d35-baaf-0bcf5a79d9c3",
      "source_ref": "centralize_posthog:derived_fixture",
      "subject_id": null,
      "unit": "events",
      "value": 1.0
    },
    {
      "account_id": "6d65226e-669f-5537-84ef-1d0e937076f3",
      "grain": "company",
      "metric_name": "centralize_action_completions",
      "observed_at": "2026-11-08T14:00:00Z",
      "signal_id": "16f86f0d-55f7-5351-a08a-b54915a7341e",
      "source_ref": "centralize_posthog:derived_fixture",
      "subject_id": null,
      "unit": "events",
      "value": 0.0
    },
    {
      "account_id": "6d65226e-669f-5537-84ef-1d0e937076f3",
      "grain": "company",
      "metric_name": "centralize_integration_sync_failures",
      "observed_at": "2026-11-08T14:00:00Z",
      "signal_id": "91ead84a-d8b4-50ff-80d2-d1023902e065",
      "source_ref": "centralize_posthog:derived_fixture",
      "subject_id": null,
      "unit": "events",
      "value": 0.0
    },
    {
      "account_id": "6d65226e-669f-5537-84ef-1d0e937076f3",
      "grain": "company",
      "metric_name": "centralize_relationship_events",
      "observed_at": "2026-11-08T14:00:00Z",
      "signal_id": "5909cbf6-89e1-5de3-9d6f-4d13f9276d95",
      "source_ref": "centralize_posthog:derived_fixture",
      "subject_id": null,
      "unit": "events",
      "value": 0.0
    },
    {
      "account_id": "6d65226e-669f-5537-84ef-1d0e937076f3",
      "grain": "company",
      "metric_name": "posthog_autocapture_events",
      "observed_at": "2026-11-08T14:00:00Z",
      "signal_id": "83d3e80d-c1b0-5ec0-a042-5104d5c1699b",
      "source_ref": "centralize_posthog:derived_fixture",
      "subject_id": null,
      "unit": "events",
      "value": 4.0
    },
    {
      "account_id": "6d65226e-669f-5537-84ef-1d0e937076f3",
      "grain": "company",
      "metric_name": "posthog_frontend_exceptions",
      "observed_at": "2026-11-08T14:00:00Z",
      "signal_id": "c0e983af-e309-57ba-8580-1954948c5ab3",
      "source_ref": "centralize_posthog:derived_fixture",
      "subject_id": null,
      "unit": "events",
      "value": 0.0
    },
    {
      "account_id": "6d65226e-669f-5537-84ef-1d0e937076f3",
      "grain": "company",
      "metric_name": "posthog_session_recordings",
      "observed_at": "2026-11-08T14:00:00Z",
      "signal_id": "759b1e0c-6d78-5563-a4fa-815a84900476",
      "source_ref": "centralize_posthog:derived_fixture",
      "subject_id": null,
      "unit": "events",
      "value": 4.0
    }
  ],
  "posthog_events": [
    {
      "account_id": "6d65226e-669f-5537-84ef-1d0e937076f3",
      "confidence": "observed_config",
      "contains_console_logs": false,
      "contains_exception": false,
      "current_url": "https://app.usecentralize.com/account/6d65226e-669f-5537-84ef-1d0e937076f3/reporting",
      "day_offset": 140,
      "distinct_id": "281dd88f-f144-5e89-8e2b-6d9501f8063c",
      "event": "$pageview",
      "event_id": "7476d9dc-1331-541c-9fd3-a2d77d88b61d",
      "observed_at": "2026-11-08T00:00:00Z",
      "properties": {
        "$browser": "Edge",
        "$pathname": "/account/6d65226e-669f-5537-84ef-1d0e937076f3/reporting",
        "$session_id": "56982d35-b6d1-5572-8272-b707dc68101a",
        "account_archetype": "risk_watch",
        "centralize_account_id": "6d65226e-669f-5537-84ef-1d0e937076f3",
        "network_timing_ms": 853,
        "organization_id": "org_fleetops",
        "perturbation_bucket": 11,
        "posthog_surface": "web_app"
      },
      "replay_ref": "posthog:recording:56982d35-b6d1-5572-8272-b707dc68101a",
      "session_id": "56982d35-b6d1-5572-8272-b707dc68101a"
    },
    {
      "account_id": "6d65226e-669f-5537-84ef-1d0e937076f3",
      "confidence": "observed_config",
      "contains_console_logs": false,
      "contains_exception": false,
      "current_url": "https://app.usecentralize.com/account/6d65226e-669f-5537-84ef-1d0e937076f3/reporting",
      "day_offset": 140,
      "distinct_id": "281dd88f-f144-5e89-8e2b-6d9501f8063c",
      "event": "$autocapture",
      "event_id": "f828698c-920b-50a7-b07e-19c55d86fee1",
      "observed_at": "2026-11-08T01:00:00Z",
      "properties": {
        "$browser": "Edge",
        "$pathname": "/account/6d65226e-669f-5537-84ef-1d0e937076f3/reporting",
        "$session_id": "56982d35-b6d1-5572-8272-b707dc68101a",
        "account_archetype": "risk_watch",
        "centralize_account_id": "6d65226e-669f-5537-84ef-1d0e937076f3",
        "element": "button",
        "network_timing_ms": 853,
        "organization_id": "org_fleetops",
        "perturbation_bucket": 11,
        "text": "Risk action"
      },
      "replay_ref": "posthog:recording:56982d35-b6d1-5572-8272-b707dc68101a",
      "session_id": "56982d35-b6d1-5572-8272-b707dc68101a"
    },
    {
      "account_id": "6d65226e-669f-5537-84ef-1d0e937076f3",
      "confidence": "observed_config",
      "contains_console_logs": false,
      "contains_exception": false,
      "current_url": "https://app.usecentralize.com/account/6d65226e-669f-5537-84ef-1d0e937076f3/contacts",
      "day_offset": 140,
      "distinct_id": "281dd88f-f144-5e89-8e2b-6d9501f8063c",
      "event": "$pageview",
      "event_id": "8b62251a-a885-5f3b-8eed-64f97b775126",
      "observed_at": "2026-11-08T00:00:00Z",
      "properties": {
        "$browser": "Safari",
        "$pathname": "/account/6d65226e-669f-5537-84ef-1d0e937076f3/contacts",
        "$session_id": "e90b9a28-b6b4-508e-a630-79d06316a538",
        "account_archetype": "risk_watch",
        "centralize_account_id": "6d65226e-669f-5537-84ef-1d0e937076f3",
        "network_timing_ms": 843,
        "organization_id": "org_fleetops",
        "perturbation_bucket": 11,
        "posthog_surface": "web_app"
      },
      "replay_ref": "posthog:recording:e90b9a28-b6b4-508e-a630-79d06316a538",
      "session_id": "e90b9a28-b6b4-508e-a630-79d06316a538"
    },
    {
      "account_id": "6d65226e-669f-5537-84ef-1d0e937076f3",
      "confidence": "observed_config",
      "contains_console_logs": false,
      "contains_exception": false,
      "current_url": "https://app.usecentralize.com/account/6d65226e-669f-5537-84ef-1d0e937076f3/contacts",
      "day_offset": 140,
      "distinct_id": "281dd88f-f144-5e89-8e2b-6d9501f8063c",
      "event": "$autocapture",
      "event_id": "75efc331-f302-568b-9712-fd1bc947e58c",
      "observed_at": "2026-11-08T01:00:00Z",
      "properties": {
        "$browser": "Safari",
        "$pathname": "/account/6d65226e-669f-5537-84ef-1d0e937076f3/contacts",
        "$session_id": "e90b9a28-b6b4-508e-a630-79d06316a538",
        "account_archetype": "risk_watch",
        "centralize_account_id": "6d65226e-669f-5537-84ef-1d0e937076f3",
        "element": "tab",
        "network_timing_ms": 843,
        "organization_id": "org_fleetops",
        "perturbation_bucket": 11,
        "text": "Champion"
      },
      "replay_ref": "posthog:recording:e90b9a28-b6b4-508e-a630-79d06316a538",
      "session_id": "e90b9a28-b6b4-508e-a630-79d06316a538"
    },
    {
      "account_id": "6d65226e-669f-5537-84ef-1d0e937076f3",
      "confidence": "observed_config",
      "contains_console_logs": false,
      "contains_exception": false,
      "current_url": "https://app.usecentralize.com/account/6d65226e-669f-5537-84ef-1d0e937076f3/actions",
      "day_offset": 140,
      "distinct_id": "281dd88f-f144-5e89-8e2b-6d9501f8063c",
      "event": "$pageview",
      "event_id": "25b3538d-ff7f-5d56-8ac9-33ae0ea80902",
      "observed_at": "2026-11-08T01:00:00Z",
      "properties": {
        "$browser": "Chrome",
        "$pathname": "/account/6d65226e-669f-5537-84ef-1d0e937076f3/actions",
        "$session_id": "997b563e-bb20-5ea5-806a-59b6e13c858f",
        "account_archetype": "risk_watch",
        "centralize_account_id": "6d65226e-669f-5537-84ef-1d0e937076f3",
        "network_timing_ms": 866,
        "organization_id": "org_fleetops",
        "perturbation_bucket": 11,
        "posthog_surface": "web_app"
      },
      "replay_ref": "posthog:recording:997b563e-bb20-5ea5-806a-59b6e13c858f",
      "session_id": "997b563e-bb20-5ea5-806a-59b6e13c858f"
    },
    {
      "account_id": "6d65226e-669f-5537-84ef-1d0e937076f3",
      "confidence": "observed_config",
      "contains_console_logs": false,
      "contains_exception": false,
      "current_url": "https://app.usecentralize.com/account/6d65226e-669f-5537-84ef-1d0e937076f3/actions",
      "day_offset": 140,
      "distinct_id": "281dd88f-f144-5e89-8e2b-6d9501f8063c",
      "event": "$autocapture",
      "event_id": "89790ac0-6cae-51f2-b241-1d9a89fe2222",
      "observed_at": "2026-11-08T02:00:00Z",
      "properties": {
        "$browser": "Chrome",
        "$pathname": "/account/6d65226e-669f-5537-84ef-1d0e937076f3/actions",
        "$session_id": "997b563e-bb20-5ea5-806a-59b6e13c858f",
        "account_archetype": "risk_watch",
        "centralize_account_id": "6d65226e-669f-5537-84ef-1d0e937076f3",
        "element": "link",
        "network_timing_ms": 866,
        "organization_id": "org_fleetops",
        "perturbation_bucket": 11,
        "text": "Health"
      },
      "replay_ref": "posthog:recording:997b563e-bb20-5ea5-806a-59b6e13c858f",
      "session_id": "997b563e-bb20-5ea5-806a-59b6e13c858f"
    },
    {
      "account_id": "6d65226e-669f-5537-84ef-1d0e937076f3",
      "confidence": "observed_config",
      "contains_console_logs": false,
      "contains_exception": false,
      "current_url": "https://app.usecentralize.com/account/6d65226e-669f-5537-84ef-1d0e937076f3/reporting",
      "day_offset": 140,
      "distinct_id": "281dd88f-f144-5e89-8e2b-6d9501f8063c",
      "event": "$pageview",
      "event_id": "65a2eef2-28a4-54cd-a6e3-4c5c2cce93d3",
      "observed_at": "2026-11-08T02:00:00Z",
      "properties": {
        "$browser": "Chrome",
        "$pathname": "/account/6d65226e-669f-5537-84ef-1d0e937076f3/reporting",
        "$session_id": "4ea9bbf6-cd80-5b34-9ea4-02b62b9d39b7",
        "account_archetype": "risk_watch",
        "centralize_account_id": "6d65226e-669f-5537-84ef-1d0e937076f3",
        "network_timing_ms": 890,
        "organization_id": "org_fleetops",
        "perturbation_bucket": 11,
        "posthog_surface": "web_app"
      },
      "replay_ref": "posthog:recording:4ea9bbf6-cd80-5b34-9ea4-02b62b9d39b7",
      "session_id": "4ea9bbf6-cd80-5b34-9ea4-02b62b9d39b7"
    },
    {
      "account_id": "6d65226e-669f-5537-84ef-1d0e937076f3",
      "confidence": "observed_config",
      "contains_console_logs": false,
      "contains_exception": false,
      "current_url": "https://app.usecentralize.com/account/6d65226e-669f-5537-84ef-1d0e937076f3/reporting",
      "day_offset": 140,
      "distinct_id": "281dd88f-f144-5e89-8e2b-6d9501f8063c",
      "event": "$autocapture",
      "event_id": "ea7de345-12e3-57c0-aee8-3d643d47c1ed",
      "observed_at": "2026-11-08T03:00:00Z",
      "properties": {
        "$browser": "Chrome",
        "$pathname": "/account/6d65226e-669f-5537-84ef-1d0e937076f3/reporting",
        "$session_id": "4ea9bbf6-cd80-5b34-9ea4-02b62b9d39b7",
        "account_archetype": "risk_watch",
        "centralize_account_id": "6d65226e-669f-5537-84ef-1d0e937076f3",
        "element": "input",
        "network_timing_ms": 890,
        "organization_id": "org_fleetops",
        "perturbation_bucket": 11,
        "text": "Timeline"
      },
      "replay_ref": "posthog:recording:4ea9bbf6-cd80-5b34-9ea4-02b62b9d39b7",
      "session_id": "4ea9bbf6-cd80-5b34-9ea4-02b62b9d39b7"
    }
  ]
}
