{
  "account_id": "ae26977b-dc41-5d46-a9cd-7ed932c68d63",
  "account_name": "Yellowpine Fleet Services",
  "account_slug": "yellowpine-fleet-services",
  "app_events": [
    {
      "account_id": "ae26977b-dc41-5d46-a9cd-7ed932c68d63",
      "confidence": "synthetic_truth",
      "day_offset": 140,
      "event_id": "e34995d2-1a06-59c9-b45a-6720f82b68d3",
      "event_type": "account_viewed",
      "feature": "account_workspace",
      "object_id": "306b072a-7492-5518-9b9c-74a31895d7da",
      "object_type": "account",
      "observed_at": "2026-11-08T00:00:00Z",
      "properties": {
        "archetype": "risk_watch",
        "health_band": "yellow",
        "lifecycle_stage": "steady_state",
        "perturbation_bucket": 9
      },
      "route": "/account/ae26977b-dc41-5d46-a9cd-7ed932c68d63",
      "source_ref": "centralize_app:mcp_api_simulated",
      "user_id": "csm-103"
    },
    {
      "account_id": "ae26977b-dc41-5d46-a9cd-7ed932c68d63",
      "confidence": "synthetic_truth",
      "day_offset": 140,
      "event_id": "b8b6907b-1bf0-5d9f-bc27-ea514a0f19b9",
      "event_type": "health_record_viewed",
      "feature": "health",
      "object_id": "589d6b95-54f2-5ed5-be40-c1b7afc3cc79",
      "object_type": "health_score",
      "observed_at": "2026-11-08T01:00:00Z",
      "properties": {
        "acted": false,
        "archetype": "risk_watch",
        "current_band": "yellow",
        "health_band": "yellow",
        "lifecycle_stage": "steady_state",
        "perturbation_bucket": 9
      },
      "route": "/account/ae26977b-dc41-5d46-a9cd-7ed932c68d63/reporting",
      "source_ref": "centralize_app:mcp_api_simulated",
      "user_id": "csm-103"
    },
    {
      "account_id": "ae26977b-dc41-5d46-a9cd-7ed932c68d63",
      "confidence": "synthetic_truth",
      "day_offset": 140,
      "event_id": "86552b9a-a10c-54cf-83ba-2b1499d7e6c6",
      "event_type": "contact_profile_opened",
      "feature": "contacts",
      "object_id": "666eb0ce-c794-57cc-917e-9df20e9305aa",
      "object_type": "contact",
      "observed_at": "2026-11-08T02:00:00Z",
      "properties": {
        "archetype": "risk_watch",
        "contact_role": "champion",
        "engagement_state": "active",
        "health_band": "yellow",
        "lifecycle_stage": "steady_state",
        "perturbation_bucket": 9
      },
      "route": "/account/ae26977b-dc41-5d46-a9cd-7ed932c68d63/contacts",
      "source_ref": "centralize_app:mcp_api_simulated",
      "user_id": "csm-103"
    },
    {
      "account_id": "ae26977b-dc41-5d46-a9cd-7ed932c68d63",
      "confidence": "inferred_route",
      "day_offset": 140,
      "event_id": "428648f1-e744-5c9d-80e1-73d8d6766a9c",
      "event_type": "saved_view_opened",
      "feature": "accounts",
      "object_id": "c5beb030-0f77-51f7-8a3a-8fb7fbc17c9c",
      "object_type": "saved_view",
      "observed_at": "2026-11-08T04:00:00Z",
      "properties": {
        "active_users": 12,
        "archetype": "risk_watch",
        "health_band": "yellow",
        "lifecycle_stage": "steady_state",
        "noise_class": "perturbed_app_exhaust",
        "perturbation_bucket": 9
      },
      "route": "/accounts",
      "source_ref": "centralize_app:mcp_api_simulated",
      "user_id": "csm-103"
    },
    {
      "account_id": "ae26977b-dc41-5d46-a9cd-7ed932c68d63",
      "confidence": "inferred_route",
      "day_offset": 140,
      "event_id": "c76632ea-97a6-523c-b910-e114f010a8f7",
      "event_type": "contact_search_performed",
      "feature": "contacts",
      "object_id": "6cd4c4b4-4c6e-5b26-9d64-124b5cfcebb5",
      "object_type": "search",
      "observed_at": "2026-11-08T05:00:00Z",
      "properties": {
        "active_users": 12,
        "archetype": "risk_watch",
        "health_band": "yellow",
        "lifecycle_stage": "steady_state",
        "noise_class": "perturbed_app_exhaust",
        "perturbation_bucket": 9
      },
      "route": "/contacts",
      "source_ref": "centralize_app:mcp_api_simulated",
      "user_id": "csm-103"
    },
    {
      "account_id": "ae26977b-dc41-5d46-a9cd-7ed932c68d63",
      "confidence": "inferred_route",
      "day_offset": 140,
      "event_id": "ebea284c-6f09-575c-b7bc-c81a8519db1b",
      "event_type": "note_viewed",
      "feature": "notes",
      "object_id": "0e1e7438-a287-514f-977b-53731dfc9925",
      "object_type": "note",
      "observed_at": "2026-11-08T06:00:00Z",
      "properties": {
        "active_users": 12,
        "archetype": "risk_watch",
        "health_band": "yellow",
        "lifecycle_stage": "steady_state",
        "noise_class": "perturbed_app_exhaust",
        "perturbation_bucket": 9
      },
      "route": "/account/ae26977b-dc41-5d46-a9cd-7ed932c68d63/notes",
      "source_ref": "centralize_app:mcp_api_simulated",
      "user_id": "csm-103"
    }
  ],
  "as_of": "2026-11-08",
  "day_offset": 140,
  "derived_usage_signals": [
    {
      "account_id": "ae26977b-dc41-5d46-a9cd-7ed932c68d63",
      "grain": "company",
      "metric_name": "centralize_account_views",
      "observed_at": "2026-11-08T14:00:00Z",
      "signal_id": "c75aac0b-b0a0-5ae5-9dd7-74ad350520dd",
      "source_ref": "centralize_posthog:derived_fixture",
      "subject_id": null,
      "unit": "events",
      "value": 1.0
    },
    {
      "account_id": "ae26977b-dc41-5d46-a9cd-7ed932c68d63",
      "grain": "company",
      "metric_name": "centralize_action_completions",
      "observed_at": "2026-11-08T14:00:00Z",
      "signal_id": "3d74bbeb-bfd0-52b2-b4f8-7f5bb3b3b643",
      "source_ref": "centralize_posthog:derived_fixture",
      "subject_id": null,
      "unit": "events",
      "value": 0.0
    },
    {
      "account_id": "ae26977b-dc41-5d46-a9cd-7ed932c68d63",
      "grain": "company",
      "metric_name": "centralize_integration_sync_failures",
      "observed_at": "2026-11-08T14:00:00Z",
      "signal_id": "87441a46-d047-50d7-a446-36fae2e77109",
      "source_ref": "centralize_posthog:derived_fixture",
      "subject_id": null,
      "unit": "events",
      "value": 0.0
    },
    {
      "account_id": "ae26977b-dc41-5d46-a9cd-7ed932c68d63",
      "grain": "company",
      "metric_name": "centralize_relationship_events",
      "observed_at": "2026-11-08T14:00:00Z",
      "signal_id": "00de25a9-3936-5252-a7d1-8b54833cf974",
      "source_ref": "centralize_posthog:derived_fixture",
      "subject_id": null,
      "unit": "events",
      "value": 0.0
    },
    {
      "account_id": "ae26977b-dc41-5d46-a9cd-7ed932c68d63",
      "grain": "company",
      "metric_name": "posthog_autocapture_events",
      "observed_at": "2026-11-08T14:00:00Z",
      "signal_id": "ab0a7e03-09c5-5b5a-a992-325c9b2b2dd4",
      "source_ref": "centralize_posthog:derived_fixture",
      "subject_id": null,
      "unit": "events",
      "value": 5.0
    },
    {
      "account_id": "ae26977b-dc41-5d46-a9cd-7ed932c68d63",
      "grain": "company",
      "metric_name": "posthog_frontend_exceptions",
      "observed_at": "2026-11-08T14:00:00Z",
      "signal_id": "380b5493-0ff0-52b7-8f1e-8ccb2b0ad911",
      "source_ref": "centralize_posthog:derived_fixture",
      "subject_id": null,
      "unit": "events",
      "value": 0.0
    },
    {
      "account_id": "ae26977b-dc41-5d46-a9cd-7ed932c68d63",
      "grain": "company",
      "metric_name": "posthog_session_recordings",
      "observed_at": "2026-11-08T14:00:00Z",
      "signal_id": "dd0bc22e-ec91-5128-837f-5f30d48431bc",
      "source_ref": "centralize_posthog:derived_fixture",
      "subject_id": null,
      "unit": "events",
      "value": 5.0
    }
  ],
  "posthog_events": [
    {
      "account_id": "ae26977b-dc41-5d46-a9cd-7ed932c68d63",
      "confidence": "observed_config",
      "contains_console_logs": false,
      "contains_exception": false,
      "current_url": "https://app.usecentralize.com/account/ae26977b-dc41-5d46-a9cd-7ed932c68d63/reporting",
      "day_offset": 140,
      "distinct_id": "686ed8ff-ea4c-56c7-8e51-3d48dd09b99a",
      "event": "$pageview",
      "event_id": "1c42a6dc-475b-5ce7-a9fb-2d1e3be7beac",
      "observed_at": "2026-11-08T00:00:00Z",
      "properties": {
        "$browser": "Edge",
        "$pathname": "/account/ae26977b-dc41-5d46-a9cd-7ed932c68d63/reporting",
        "$session_id": "4d9c728e-2f9e-5725-870d-e4a679a1e30e",
        "account_archetype": "risk_watch",
        "centralize_account_id": "ae26977b-dc41-5d46-a9cd-7ed932c68d63",
        "network_timing_ms": 934,
        "organization_id": "org_fleetops",
        "perturbation_bucket": 4,
        "posthog_surface": "web_app"
      },
      "replay_ref": "posthog:recording:4d9c728e-2f9e-5725-870d-e4a679a1e30e",
      "session_id": "4d9c728e-2f9e-5725-870d-e4a679a1e30e"
    },
    {
      "account_id": "ae26977b-dc41-5d46-a9cd-7ed932c68d63",
      "confidence": "observed_config",
      "contains_console_logs": false,
      "contains_exception": false,
      "current_url": "https://app.usecentralize.com/account/ae26977b-dc41-5d46-a9cd-7ed932c68d63/reporting",
      "day_offset": 140,
      "distinct_id": "686ed8ff-ea4c-56c7-8e51-3d48dd09b99a",
      "event": "$autocapture",
      "event_id": "6e6ce1c1-8312-5ced-a70b-ea79c1476006",
      "observed_at": "2026-11-08T01:00:00Z",
      "properties": {
        "$browser": "Edge",
        "$pathname": "/account/ae26977b-dc41-5d46-a9cd-7ed932c68d63/reporting",
        "$session_id": "4d9c728e-2f9e-5725-870d-e4a679a1e30e",
        "account_archetype": "risk_watch",
        "centralize_account_id": "ae26977b-dc41-5d46-a9cd-7ed932c68d63",
        "element": "button",
        "network_timing_ms": 934,
        "organization_id": "org_fleetops",
        "perturbation_bucket": 4,
        "text": "Risk action"
      },
      "replay_ref": "posthog:recording:4d9c728e-2f9e-5725-870d-e4a679a1e30e",
      "session_id": "4d9c728e-2f9e-5725-870d-e4a679a1e30e"
    },
    {
      "account_id": "ae26977b-dc41-5d46-a9cd-7ed932c68d63",
      "confidence": "observed_config",
      "contains_console_logs": false,
      "contains_exception": false,
      "current_url": "https://app.usecentralize.com/account/ae26977b-dc41-5d46-a9cd-7ed932c68d63/contacts",
      "day_offset": 140,
      "distinct_id": "686ed8ff-ea4c-56c7-8e51-3d48dd09b99a",
      "event": "$pageview",
      "event_id": "8ba3489d-d888-5606-976b-04c1bbcc09c3",
      "observed_at": "2026-11-08T00:00:00Z",
      "properties": {
        "$browser": "Safari",
        "$pathname": "/account/ae26977b-dc41-5d46-a9cd-7ed932c68d63/contacts",
        "$session_id": "49ccb915-b11a-537e-8a26-751083d20917",
        "account_archetype": "risk_watch",
        "centralize_account_id": "ae26977b-dc41-5d46-a9cd-7ed932c68d63",
        "network_timing_ms": 1025,
        "organization_id": "org_fleetops",
        "perturbation_bucket": 4,
        "posthog_surface": "web_app"
      },
      "replay_ref": "posthog:recording:49ccb915-b11a-537e-8a26-751083d20917",
      "session_id": "49ccb915-b11a-537e-8a26-751083d20917"
    },
    {
      "account_id": "ae26977b-dc41-5d46-a9cd-7ed932c68d63",
      "confidence": "observed_config",
      "contains_console_logs": false,
      "contains_exception": false,
      "current_url": "https://app.usecentralize.com/account/ae26977b-dc41-5d46-a9cd-7ed932c68d63/contacts",
      "day_offset": 140,
      "distinct_id": "686ed8ff-ea4c-56c7-8e51-3d48dd09b99a",
      "event": "$autocapture",
      "event_id": "c9dfcb83-74f7-51f0-ac9c-98916113f001",
      "observed_at": "2026-11-08T01:00:00Z",
      "properties": {
        "$browser": "Safari",
        "$pathname": "/account/ae26977b-dc41-5d46-a9cd-7ed932c68d63/contacts",
        "$session_id": "49ccb915-b11a-537e-8a26-751083d20917",
        "account_archetype": "risk_watch",
        "centralize_account_id": "ae26977b-dc41-5d46-a9cd-7ed932c68d63",
        "element": "tab",
        "network_timing_ms": 1025,
        "organization_id": "org_fleetops",
        "perturbation_bucket": 4,
        "text": "Champion"
      },
      "replay_ref": "posthog:recording:49ccb915-b11a-537e-8a26-751083d20917",
      "session_id": "49ccb915-b11a-537e-8a26-751083d20917"
    },
    {
      "account_id": null,
      "confidence": "observed_config",
      "contains_console_logs": false,
      "contains_exception": false,
      "current_url": "https://app.usecentralize.com/account/ae26977b-dc41-5d46-a9cd-7ed932c68d63/actions",
      "day_offset": 140,
      "distinct_id": "686ed8ff-ea4c-56c7-8e51-3d48dd09b99a",
      "event": "$pageview",
      "event_id": "eb13a5d9-7a05-5259-8bac-eea87613e333",
      "observed_at": "2026-11-08T01:00:00Z",
      "properties": {
        "$browser": "Chrome",
        "$pathname": "/account/ae26977b-dc41-5d46-a9cd-7ed932c68d63/actions",
        "$session_id": "82463b90-350c-55af-ad24-16a05535b224",
        "account_archetype": "risk_watch",
        "centralize_account_id": "ae26977b-dc41-5d46-a9cd-7ed932c68d63",
        "network_timing_ms": 1036,
        "organization_id": "org_fleetops",
        "perturbation_bucket": 4,
        "posthog_surface": "web_app"
      },
      "replay_ref": "posthog:recording:82463b90-350c-55af-ad24-16a05535b224",
      "session_id": "82463b90-350c-55af-ad24-16a05535b224"
    },
    {
      "account_id": null,
      "confidence": "observed_config",
      "contains_console_logs": false,
      "contains_exception": false,
      "current_url": "https://app.usecentralize.com/account/ae26977b-dc41-5d46-a9cd-7ed932c68d63/actions",
      "day_offset": 140,
      "distinct_id": "686ed8ff-ea4c-56c7-8e51-3d48dd09b99a",
      "event": "$autocapture",
      "event_id": "01e6f3e0-bd76-5ddc-b002-2a7b3d049352",
      "observed_at": "2026-11-08T02:00:00Z",
      "properties": {
        "$browser": "Chrome",
        "$pathname": "/account/ae26977b-dc41-5d46-a9cd-7ed932c68d63/actions",
        "$session_id": "82463b90-350c-55af-ad24-16a05535b224",
        "account_archetype": "risk_watch",
        "centralize_account_id": "ae26977b-dc41-5d46-a9cd-7ed932c68d63",
        "element": "link",
        "network_timing_ms": 1036,
        "organization_id": "org_fleetops",
        "perturbation_bucket": 4,
        "text": "Health"
      },
      "replay_ref": "posthog:recording:82463b90-350c-55af-ad24-16a05535b224",
      "session_id": "82463b90-350c-55af-ad24-16a05535b224"
    },
    {
      "account_id": "ae26977b-dc41-5d46-a9cd-7ed932c68d63",
      "confidence": "observed_config",
      "contains_console_logs": false,
      "contains_exception": false,
      "current_url": "https://app.usecentralize.com/account/ae26977b-dc41-5d46-a9cd-7ed932c68d63/reporting",
      "day_offset": 140,
      "distinct_id": "686ed8ff-ea4c-56c7-8e51-3d48dd09b99a",
      "event": "$pageview",
      "event_id": "1e11d60d-0eec-516b-a424-e228e46e7ae5",
      "observed_at": "2026-11-08T02:00:00Z",
      "properties": {
        "$browser": "Chrome",
        "$pathname": "/account/ae26977b-dc41-5d46-a9cd-7ed932c68d63/reporting",
        "$session_id": "cff2ee44-2734-52ae-a2bd-e73543876ff6",
        "account_archetype": "risk_watch",
        "centralize_account_id": "ae26977b-dc41-5d46-a9cd-7ed932c68d63",
        "network_timing_ms": 1137,
        "organization_id": "org_fleetops",
        "perturbation_bucket": 4,
        "posthog_surface": "web_app"
      },
      "replay_ref": "posthog:recording:cff2ee44-2734-52ae-a2bd-e73543876ff6",
      "session_id": "cff2ee44-2734-52ae-a2bd-e73543876ff6"
    },
    {
      "account_id": "ae26977b-dc41-5d46-a9cd-7ed932c68d63",
      "confidence": "observed_config",
      "contains_console_logs": false,
      "contains_exception": false,
      "current_url": "https://app.usecentralize.com/account/ae26977b-dc41-5d46-a9cd-7ed932c68d63/reporting",
      "day_offset": 140,
      "distinct_id": "686ed8ff-ea4c-56c7-8e51-3d48dd09b99a",
      "event": "$autocapture",
      "event_id": "e3e548e8-0907-5444-91e9-17b675afd03d",
      "observed_at": "2026-11-08T03:00:00Z",
      "properties": {
        "$browser": "Chrome",
        "$pathname": "/account/ae26977b-dc41-5d46-a9cd-7ed932c68d63/reporting",
        "$session_id": "cff2ee44-2734-52ae-a2bd-e73543876ff6",
        "account_archetype": "risk_watch",
        "centralize_account_id": "ae26977b-dc41-5d46-a9cd-7ed932c68d63",
        "element": "input",
        "network_timing_ms": 1137,
        "organization_id": "org_fleetops",
        "perturbation_bucket": 4,
        "text": "Timeline"
      },
      "replay_ref": "posthog:recording:cff2ee44-2734-52ae-a2bd-e73543876ff6",
      "session_id": "cff2ee44-2734-52ae-a2bd-e73543876ff6"
    },
    {
      "account_id": "ae26977b-dc41-5d46-a9cd-7ed932c68d63",
      "confidence": "observed_config",
      "contains_console_logs": false,
      "contains_exception": false,
      "current_url": "https://app.usecentralize.com/account/ae26977b-dc41-5d46-a9cd-7ed932c68d63/contacts",
      "day_offset": 140,
      "distinct_id": "686ed8ff-ea4c-56c7-8e51-3d48dd09b99a",
      "event": "$pageview",
      "event_id": "f9bde69c-5a08-5636-bd2c-054df4477145",
      "observed_at": "2026-11-08T03:00:00Z",
      "properties": {
        "$browser": "Chrome",
        "$pathname": "/account/ae26977b-dc41-5d46-a9cd-7ed932c68d63/contacts",
        "$session_id": "ee7d2334-a6d3-5a99-8637-0cde85752e6c",
        "account_archetype": "risk_watch",
        "centralize_account_id": "ae26977b-dc41-5d46-a9cd-7ed932c68d63",
        "network_timing_ms": 883,
        "organization_id": "org_fleetops",
        "perturbation_bucket": 4,
        "posthog_surface": "web_app"
      },
      "replay_ref": "posthog:recording:ee7d2334-a6d3-5a99-8637-0cde85752e6c",
      "session_id": "ee7d2334-a6d3-5a99-8637-0cde85752e6c"
    },
    {
      "account_id": "ae26977b-dc41-5d46-a9cd-7ed932c68d63",
      "confidence": "observed_config",
      "contains_console_logs": false,
      "contains_exception": false,
      "current_url": "https://app.usecentralize.com/account/ae26977b-dc41-5d46-a9cd-7ed932c68d63/contacts",
      "day_offset": 140,
      "distinct_id": "686ed8ff-ea4c-56c7-8e51-3d48dd09b99a",
      "event": "$autocapture",
      "event_id": "bb30ebe9-7b37-5e85-bd7e-7d4601ebf8c7",
      "observed_at": "2026-11-08T04:00:00Z",
      "properties": {
        "$browser": "Chrome",
        "$pathname": "/account/ae26977b-dc41-5d46-a9cd-7ed932c68d63/contacts",
        "$session_id": "ee7d2334-a6d3-5a99-8637-0cde85752e6c",
        "account_archetype": "risk_watch",
        "centralize_account_id": "ae26977b-dc41-5d46-a9cd-7ed932c68d63",
        "element": "button",
        "network_timing_ms": 883,
        "organization_id": "org_fleetops",
        "perturbation_bucket": 4,
        "text": "Risk action"
      },
      "replay_ref": "posthog:recording:ee7d2334-a6d3-5a99-8637-0cde85752e6c",
      "session_id": "ee7d2334-a6d3-5a99-8637-0cde85752e6c"
    }
  ]
}
